analysis/gather_results.py
analysis/json_log_viewer/json_log_viewer.py
analysis/sft_data_viewer/sft_data_viewer.py
analysis/tool_use/episode_length.py
analysis/tool_use/incorrect_arguments.py
analysis/tool_use/response_tokens.py
analysis/tool_use/tool_use_categories.py
data/mini_nightmare/config/config_code.py
data/mini_nightmare/config/test.py
data/mini_nightmare/counter/counter_code.py
data/mini_nightmare/counter/test.py
data/mini_nightmare/grader/grader_code.py
data/mini_nightmare/grader/test.py
data/mini_nightmare/pandas_dataframe/pandas_dataframe_code.py
data/mini_nightmare/pandas_dataframe/test.py
data/mini_nightmare/patcher/patcher_code.py
data/mini_nightmare/patcher/test.py
data/mini_nightmare/purr/purr_code.py
data/mini_nightmare/purr/test.py
data/mini_nightmare/scientific_calculator/scientific_calculator_code.py
data/mini_nightmare/scientific_calculator/scientific_calculator_tool.py
data/mini_nightmare/scientific_calculator/test.py
data/mini_nightmare/shopping_cart/shopping_cart_code.py
data/mini_nightmare/shopping_cart/test.py
data/mini_nightmare/sum_tree/sum_tree_code.py
data/mini_nightmare/sum_tree/test.py
data/mini_nightmare/tomorrow_date/test.py
data/mini_nightmare/tomorrow_date/tomorrow_date_code.py
data/pytorch/pytorch_code.py
data/pytorch/test.py
debug_gym/__init__.py
debug_gym/constants.py
debug_gym/experiment.py
debug_gym/logger.py
debug_gym/version.py
debug_gym/agents/__init__.py
debug_gym/agents/base_agent.py
debug_gym/agents/froggy_agent.py
debug_gym/agents/history_tracker.py
debug_gym/agents/simple_agent.py
debug_gym/agents/solution_agent.py
debug_gym/agents/utils.py
debug_gym/gym/__init__.py
debug_gym/gym/entities.py
debug_gym/gym/utils.py
debug_gym/gym/workspace.py
debug_gym/gym/envs/__init__.py
debug_gym/gym/envs/aider.py
debug_gym/gym/envs/env.py
debug_gym/gym/envs/free_env.py
debug_gym/gym/envs/local.py
debug_gym/gym/envs/mini_nightmare.py
debug_gym/gym/envs/r2egym.py
debug_gym/gym/envs/swe_bench.py
debug_gym/gym/envs/swe_bench_debug.py
debug_gym-1.3.0.dist-info/licenses/LICENSE
debug_gym-1.3.0.dist-info/METADATA
debug_gym-1.3.0.dist-info/WHEEL
debug_gym-1.3.0.dist-info/top_level.txt
debug_gym-1.3.0.dist-info/RECORD
