Metadata-Version: 2.4
Name: debug-gym
Version: 1.3.0
Summary: debug-gym - interactive debugging environment
Project-URL: Homepage, https://aka.ms/debug-gym
Project-URL: Repository, https://github.com/microsoft/debug-gym
Project-URL: Issues, https://github.com/microsoft/debug-gym/issues
Project-URL: Changelog, https://github.com/microsoft/debug-gym/blob/main/CHANGELOG.md
Classifier: Programming Language :: Python :: 3
Classifier: License :: OSI Approved :: MIT License
Classifier: Operating System :: OS Independent
Requires-Python: >=3.12
License-File: LICENSE
Requires-Dist: datasets==3.6.0
Requires-Dist: openai==1.99.9
Requires-Dist: azure-identity==1.22.0
Requires-Dist: tenacity==9.1.2
Requires-Dist: pyyaml==6.0.2
Requires-Dist: pytest==8.3.5
Requires-Dist: gitignore_parser==0.1.12
Requires-Dist: termcolor==3.1.0
Requires-Dist: transformers==4.51.3
Requires-Dist: tiktoken
Requires-Dist: docker==7.1.0
Requires-Dist: swebench==4.0.3
Requires-Dist: swesmith==0.0.4
Requires-Dist: prompt_toolkit==3.0.51
Requires-Dist: anthropic==0.51.0
Requires-Dist: jinja2==3.1.6
Requires-Dist: rich==14.0.0
Requires-Dist: kubernetes==33.1.0
Provides-Extra: dev
Requires-Dist: pytest; extra == "dev"
Requires-Dist: pytest-asyncio; extra == "dev"
Requires-Dist: pytest-cov; extra == "dev"
Requires-Dist: pytest-xdist; extra == "dev"
Requires-Dist: pytest-timeout; extra == "dev"
Requires-Dist: pytest-env; extra == "dev"
Requires-Dist: isort; extra == "dev"
Requires-Dist: black; extra == "dev"
Dynamic: license-file
